{"rows": [{"c": [{"v": "INTRODUCED HOUSE"}, {"v": 38.91563636363637}]}, {"c": [{"v": "PASS HOUSE COMMITTEE"}, {"v": 14.845338983050848}]}, {"c": [{"v": "PASS HOUSE"}, {"v": 2.44921875}]}, {"c": [{"v": "INTRODUCED SENATE"}, {"v": 6.1683168316831685}]}, {"c": [{"v": "PASS SENATE COMMITTEE"}, {"v": 5.024539877300613}]}, {"c": [{"v": "PASS SENATE"}, {"v": 0.0}]}, {"c": [{"v": "PASS CONFERENCE COMMITTEE"}, {"v": 0.0}]}], "cols": [{"type": "string", "id": "stage", "label": "Stage"}, {"type": "number", "id": "avg", "label": "Average Duration"}]}